{
  "type": "minecraft:crafting_shaped",
  "pattern":
  [
    "W W",
    "SNS",
    "W W"
  ],
  "key":
  {
    "N":
    {
      "tag": "tfc:axes"
    },
    "S":
    [
      {
        "tag": "tfc:igneous_intrusive_rock"
      },
      {
        "tag": "tfc:sedimentary_rock"
      },
      {
        "tag": "tfc:igneous_extrusive_rock"
      },
      {
        "tag": "tfc:metamorphic_rock"
      }
    ],
    "W":
    {
      "tag": "minecraft:logs"
    }
  },
  "result":
  {
    "item": "domum_ornamentum:architectscutter",
    "count": 1
  }
}